tdb_io/h5t.py
tdb_io/h5toinfl.py
tdb_io/influx.py
tdb_io/mongo.py
tdb_io/org2h5.py
tdb_io/version.py
tdb_io-0.7.9.data/scripts/tdb_io
tdb_io-0.7.9.dist-info/METADATA
tdb_io-0.7.9.dist-info/WHEEL
tdb_io-0.7.9.dist-info/top_level.txt
tdb_io-0.7.9.dist-info/RECORD
