Metadata-Version: 2.1
Name: tdb_io
Version: 0.7.9
Summary: tool to fast look into influxdb and insert data from python
Author: jaromrax
Author-email: jaromrax@gmail.com
License: GPL2
Requires-Dist: pymongo
Requires-Dist: matplotlib
Requires-Dist: argparse
Requires-Dist: pandas
Requires-Dist: numpy
Requires-Dist: datetime
Requires-Dist: fire
Requires-Dist: influxdb
Requires-Dist: drawilleplot
Requires-Dist: tzlocal
